LICENSE
MANIFEST.in
README.md
setup.py
src/validr/__init__.py
src/validr/_exception_c.c
src/validr/_exception_c.pyx
src/validr/_exception_py.py
src/validr/_validator_c.c
src/validr/_validator_c.pyx
src/validr/_validator_py.py
src/validr/exception.py
src/validr/model.py
src/validr/model.pyi
src/validr/schema.py
src/validr/schema.pyi
src/validr/validator.py
src/validr.egg-info/PKG-INFO
src/validr.egg-info/SOURCES.txt
src/validr.egg-info/dependency_links.txt
src/validr.egg-info/not-zip-safe
src/validr.egg-info/requires.txt
src/validr.egg-info/top_level.txt
src/validr/_vendor/__init__.py
src/validr/_vendor/durationpy.py
src/validr/_vendor/email_validator.py
src/validr/_vendor/fqdn.py