Metadata-Version: 2.1
Name: validr
Version: 1.2.1
Summary: A simple, fast, extensible python library for data validation.
Home-page: https://github.com/guyskk/validr
Author: guyskk
Author-email: guyskk@qq.com
License: MIT
Keywords: validation validator validate schema jsonschema
Platform: UNKNOWN
Classifier: Intended Audience :: Developers
Classifier: License :: OSI Approved :: MIT License
Classifier: Operating System :: OS Independent
Classifier: Programming Language :: Python :: 3 :: Only
Classifier: Topic :: Software Development :: Libraries :: Python Modules
Provides-Extra: dev
Provides-Extra: benchmark
